cvbankas_scraper
