Metadata-Version: 1.0
Name: cvbankas-scraper
Version: 0.0.7
Summary: cvbankas.lt web site scraper
Home-page: https://github.com/tomasrasymas/cvbankas_scraper
Author: Tomas Rasymas
Author-email: tomas.rasymas@gmail.com
License: MIT
Platform: UNKNOWN
